{
    "players": [
        {
            "playerName": "VeryNiceAshe",
            "playerMMR": 214,
            "playerGames": 1,
            "playerWinRate": 0,
            "playerCharacterStats": [
                {
                    "playerCharacterCode": "Sissela Mini",
                    "playerCharacterPickRate": 100.0
                }
            ],
            "playerTwitch": "xVeryNiceAshe"
        },
        {
            "playerName": "SmugDragon",
            "playerMMR": 0,
            "playerGames": 0,
            "playerWinRate": 0,
            "playerCharacterStats": null,
            "playerTwitch": "SmugDragonER"
        },
        {
            "playerName": "SalmonFish",
            "playerMMR": 0,
            "playerGames": 0,
            "playerWinRate": 0,
            "playerCharacterStats": null,
            "playerTwitch": "iSalmonFish"
        },
        {
            "playerName": "MajinTenshinhan",
            "playerMMR": 0,
            "playerGames": 0,
            "playerWinRate": 0,
            "playerCharacterStats": null,
            "playerTwitch": "MajinTenshinhan"
        },
        {
            "playerName": "ImpVivi",
            "playerMMR": 0,
            "playerGames": 0,
            "playerWinRate": 0,
            "playerCharacterStats": null,
            "playerTwitch": "Imp_Vivi"
        },
        {
            "playerName": "kspiegler",
            "playerMMR": 0,
            "playerGames": 0,
            "playerWinRate": 0,
            "playerCharacterStats": null,
            "playerTwitch": "kspiegler"
        },
        {
            "playerName": "Arky\u30fc",
            "playerMMR": 0,
            "playerGames": 0,
            "playerWinRate": 0,
            "playerCharacterStats": null,
            "playerTwitch": "Arky_ER"
        },
        {
            "playerName": "Quip",
            "playerMMR": 0,
            "playerGames": 0,
            "playerWinRate": 0,
            "playerCharacterStats": null,
            "playerTwitch": "quip_er"
        },
        {
            "playerName": "Leitnessen",
            "playerMMR": 0,
            "playerGames": 0,
            "playerWinRate": 0,
            "playerCharacterStats": null,
            "playerTwitch": "Leitnessen"
        },
        {
            "playerName": "Johnjuice",
            "playerMMR": 0,
            "playerGames": 0,
            "playerWinRate": 0,
            "playerCharacterStats": null,
            "playerTwitch": "Johnjuice"
        },
        {
            "playerName": "HajtoNaMotorze",
            "playerMMR": 0,
            "playerGames": 0,
            "playerWinRate": 0,
            "playerCharacterStats": null,
            "playerTwitch": "hajtonamotorze"
        },
        {
            "playerName": "Connax",
            "playerMMR": 0,
            "playerGames": 0,
            "playerWinRate": 0,
            "playerCharacterStats": null,
            "playerTwitch": "connax_"
        },
        {
            "playerName": "Baumi",
            "playerMMR": 0,
            "playerGames": 0,
            "playerWinRate": 0,
            "playerCharacterStats": null,
            "playerTwitch": "baumi_er"
        },
        {
            "playerName": "Aghilas",
            "playerMMR": 0,
            "playerGames": 0,
            "playerWinRate": 0,
            "playerCharacterStats": null,
            "playerTwitch": "Aghilask"
        },
        {
            "playerName": "INTA",
            "playerMMR": 0,
            "playerGames": 0,
            "playerWinRate": 0,
            "playerCharacterStats": null,
            "playerTwitch": "Kudetaa"
        },
        {
            "playerName": "Pom",
            "playerMMR": 0,
            "playerGames": 0,
            "playerWinRate": 0,
            "playerCharacterStats": null,
            "playerTwitch": "reapom"
        },
        {
            "playerName": "MoskesAcabe",
            "playerMMR": 0,
            "playerGames": 0,
            "playerWinRate": 0,
            "playerCharacterStats": null,
            "playerTwitch": "MoskesAcabe"
        },
        {
            "playerName": "GuiltyChallenger",
            "playerMMR": 0,
            "playerGames": 0,
            "playerWinRate": 0,
            "playerCharacterStats": null,
            "playerTwitch": "itsmebobou"
        },
        {
            "playerName": "FishyFishy",
            "playerMMR": 0,
            "playerGames": 0,
            "playerWinRate": 0,
            "playerCharacterStats": null,
            "playerTwitch": "FishyFishy__"
        },
        {
            "playerName": "Yazidron",
            "playerMMR": 0,
            "playerGames": 0,
            "playerWinRate": 0,
            "playerCharacterStats": null,
            "playerTwitch": "yazidron"
        },
        {
            "playerName": "FDGood",
            "playerMMR": 0,
            "playerGames": 0,
            "playerWinRate": 0,
            "playerCharacterStats": null,
            "playerTwitch": "FDGoodVX"
        },
        {
            "playerName": "BLM",
            "playerMMR": 0,
            "playerGames": 0,
            "playerWinRate": 0,
            "playerCharacterStats": null,
            "playerTwitch": "bumholey29"
        },
        {
            "playerName": "Patreii",
            "playerMMR": 0,
            "playerGames": 0,
            "playerWinRate": 0,
            "playerCharacterStats": null,
            "playerTwitch": "Patreii"
        },
        {
            "playerName": "LewMalpa",
            "playerMMR": 0,
            "playerGames": 0,
            "playerWinRate": 0,
            "playerCharacterStats": null,
            "playerTwitch": "ZuniM8"
        }
    ]
}